awsdf/__init__.py
awsdf/aws.py
awsdf-0.1.21.dist-info/METADATA
awsdf-0.1.21.dist-info/WHEEL
awsdf-0.1.21.dist-info/RECORD
