Metadata-Version: 2.1
Name: awsdf
Version: 0.1.21
Summary: AWS metadata as dataframes
Author: Allan
Author-email: allan.dsouza@gmail.com
Requires-Python: >=3.9,<=3.12.10
Classifier: Programming Language :: Python :: 3
Classifier: Programming Language :: Python :: 3.9
Classifier: Programming Language :: Python :: 3.10
Classifier: Programming Language :: Python :: 3.11
Classifier: Programming Language :: Python :: 3.12
Requires-Dist: awswrangler (>=3.4.2,<4.0.0)
Requires-Dist: loguru (>=0.7.2,<0.8.0)
Requires-Dist: tabulate (>=0.9.0,<0.10.0)
Requires-Dist: tqdm (>=4.66.1,<5.0.0)
